README.md
setup.py
mini_youtube_player.egg-info/PKG-INFO
mini_youtube_player.egg-info/SOURCES.txt
mini_youtube_player.egg-info/dependency_links.txt
mini_youtube_player.egg-info/entry_points.txt
mini_youtube_player.egg-info/requires.txt
mini_youtube_player.egg-info/top_level.txt
src/__main__.py