Metadata-Version: 2.1
Name: mini-youtube-player
Version: 1.0.3
Summary: CLI youtube video search and play
Home-page: https://github.com/tobip/mini-youtube-player
Author: Tobias Paar
Author-email: tobip@users.noreply.github.com
License: MIT
Platform: UNKNOWN
Classifier: License :: OSI Approved :: MIT License
Classifier: Programming Language :: Python :: 3
Classifier: Programming Language :: Python :: 3.7
Classifier: Operating System :: OS Independent
Requires-Python: >=3.4
